README.md
setup.cfg
setup.py
scikit_forecasts.egg-info/PKG-INFO
scikit_forecasts.egg-info/SOURCES.txt
scikit_forecasts.egg-info/dependency_links.txt
scikit_forecasts.egg-info/not-zip-safe
scikit_forecasts.egg-info/top_level.txt
skfore/__init__.py
skfore/case.py
skfore/datasets.py
skfore/extras.py
skfore/file_reader.py
skfore/skfore.py